personage_net/__init__.py
personage_net/settings.py
personage_net/app/__init__.py
personage_net/app/index.py
personage_net/app/main.py
personage_net/app/auth/__init__.py
personage_net/app/auth/models.py
personage_net/app/auth/routes.py
personage_net/app/instruct/__init__.py
personage_net/app/instruct/models.py
personage_net/app/instruct/routes.py
personage_net/app/sql/__init__.py
personage_net/app/sql/models.py
personage_net/app/sql/routes.py
personage_net/app/utils/__init__.py
personage_net/app/utils/routes.py
personage_net/db/__init__.py
personage_net/db/config.ini
personage_net/db/connection.py
personage_net/logs/__init__.py
personage_net/test/__init__.py
personage_net/utils/__init__.py
personage_net/utils/response.py
personage_net/utils/crypto/__init__.py
personage_net/utils/crypto/aes.py
personage_net/utils/crypto/bcrypt.py
personage_net/utils/crypto/rsa.py
personage_net/utils/jwt/__init__.py
personage_net/utils/jwt/config.py
personage_net/utils/redis/__init__.py
personage_net/utils/redis/redis_manager.py
personage_net-1.0.6.dist-info/LICENSE
personage_net-1.0.6.dist-info/METADATA
personage_net-1.0.6.dist-info/WHEEL
personage_net-1.0.6.dist-info/top_level.txt
personage_net-1.0.6.dist-info/RECORD
