Metadata-Version: 2.1
Name: personage-net
Version: 1.0.6
Summary: 一个在线工具
Home-page: https://github.com/TungTJD/personage_net.git
Author: tangjiadong
Author-email: 958999498@qq.com
Classifier: Programming Language :: Python :: 3
Classifier: License :: OSI Approved :: MIT License
Classifier: Operating System :: OS Independent
Requires-Python: >=3.12
License-File: LICENSE
Requires-Dist: aiomysql ==0.2.0
Requires-Dist: annotated-types ==0.7.0
Requires-Dist: anyio ==4.4.0
Requires-Dist: bcrypt ==4.2.0
Requires-Dist: certifi ==2024.7.4
Requires-Dist: cffi ==1.16.0
Requires-Dist: charset-normalizer ==3.3.2
Requires-Dist: click ==8.1.7
Requires-Dist: colorama ==0.4.6
Requires-Dist: cryptography ==43.0.0
Requires-Dist: dnspython ==2.6.1
Requires-Dist: docutils ==0.21.2
Requires-Dist: email-validator ==2.2.0
Requires-Dist: fastapi ==0.111.1
Requires-Dist: fastapi-cli ==0.0.4
Requires-Dist: h11 ==0.14.0
Requires-Dist: httpcore ==1.0.5
Requires-Dist: httptools ==0.6.1
Requires-Dist: httpx ==0.27.0
Requires-Dist: idna ==3.7
Requires-Dist: importlib-metadata ==8.2.0
Requires-Dist: jaraco.classes ==3.4.0
Requires-Dist: jaraco.context ==5.3.0
Requires-Dist: jaraco.functools ==4.0.1
Requires-Dist: Jinja2 ==3.1.4
Requires-Dist: keyring ==25.2.1
Requires-Dist: markdown-it-py ==3.0.0
Requires-Dist: MarkupSafe ==2.1.5
Requires-Dist: mdurl ==0.1.2
Requires-Dist: more-itertools ==10.3.0
Requires-Dist: nh3 ==0.2.18
Requires-Dist: pkginfo ==1.10.0
Requires-Dist: pycparser ==2.22
Requires-Dist: pydantic ==2.8.2
Requires-Dist: pydantic-core ==2.20.1
Requires-Dist: Pygments ==2.18.0
Requires-Dist: PyJWT ==2.9.0
Requires-Dist: PyMySQL ==1.1.1
Requires-Dist: python-dotenv ==1.0.1
Requires-Dist: python-multipart ==0.0.9
Requires-Dist: pywin32-ctypes ==0.2.2
Requires-Dist: PyYAML ==6.0.1
Requires-Dist: readme-renderer ==44.0
Requires-Dist: redis ==5.0.8
Requires-Dist: reloadium ==1.5.1
Requires-Dist: requests ==2.32.3
Requires-Dist: requests-toolbelt ==1.0.0
Requires-Dist: rfc3986 ==2.0.0
Requires-Dist: rich ==13.7.1
Requires-Dist: setuptools ==71.0.4
Requires-Dist: shellingham ==1.5.4
Requires-Dist: sniffio ==1.3.1
Requires-Dist: starlette ==0.37.2
Requires-Dist: twine ==5.1.1
Requires-Dist: typer ==0.12.3
Requires-Dist: typing-extensions ==4.12.2
Requires-Dist: urllib3 ==2.2.2
Requires-Dist: uvicorn ==0.30.3
Requires-Dist: watchfiles ==0.22.0
Requires-Dist: websockets ==12.0
Requires-Dist: wheel ==0.43.0
Requires-Dist: zipp ==3.19.2
